nl5py/__init__.py
nl5py/schematic.py
nl5py/nl5_dll/__init__.py
nl5py/nl5_dll/commands.py
nl5py/nl5_dll/nl5_dll.dll
nl5py/nl5_dll/nl5_dll.h
nl5py/nl5_dll/nl5_dll.lib
nl5py/nl5_dll/Linux/__init__.py
nl5py/nl5_dll/Linux/RHEL/__init__.py
nl5py/nl5_dll/Linux/RHEL/nl5_dll.h
nl5py/nl5_dll/Linux/RHEL/nl5_dll.so
nl5py/nl5_dll/Linux/Ubuntu/__init__.py
nl5py/nl5_dll/Linux/Ubuntu/nl5_dll.h
nl5py/nl5_dll/Linux/Ubuntu/nl5_dll.so
nl5py/nl5_dll/Windows/__init__.py
nl5py/nl5_dll/Windows/nl5_dll.dll
nl5py/nl5_dll/Windows/nl5_dll.h
nl5py/nl5_dll/Windows/nl5_dll.lib
nl5py-0.1.5.dist-info/LICENSE
nl5py-0.1.5.dist-info/METADATA
nl5py-0.1.5.dist-info/WHEEL
nl5py-0.1.5.dist-info/top_level.txt
nl5py-0.1.5.dist-info/RECORD
