Metadata-Version: 2.1
Name: nl5py
Version: 0.1.5
Summary: Python library for interfacing to the NL5 DLL based circuit simulator
Home-page: https://github.com/enphase/nl5py
Author: Donny Zimmanck
Author-email: dzimmanck@enphaseenergy.com
Classifier: Programming Language :: Python :: 3
Classifier: License :: OSI Approved :: Apache Software License
Classifier: Operating System :: Microsoft :: Windows
Classifier: Operating System :: MacOS
Classifier: Operating System :: POSIX :: Linux
Requires-Python: >=3.8
License-File: LICENSE
Requires-Dist: numpy
Requires-Dist: pandas
Requires-Dist: importlib-resources
Provides-Extra: dev
Requires-Dist: pytest; extra == "dev"
